eywa.py
eywa_reacher_client-0.0.8.dist-info/LICENSE
eywa_reacher_client-0.0.8.dist-info/WHEEL
eywa_reacher_client-0.0.8.dist-info/METADATA
eywa_reacher_client-0.0.8.dist-info/RECORD
