Metadata-Version: 2.1
Name: eywa-reacher-client
Version: 0.0.8
Summary: EYWA Reacher client
Author-email: Robert Gersak <robi@neyho.com>
Classifier: License :: OSI Approved :: MIT License
Project-URL: Home, https://www.neyho.com
